kdrive_client/__init__.py
kdrive_client/kdrive_api_error.py
kdrive_client/kdrive_chunk.py
kdrive_client/kdrive_client.py
kdrive_client/kdrive_file.py
kdriveclientpy-1.0.5.dist-info/METADATA
kdriveclientpy-1.0.5.dist-info/WHEEL
kdriveclientpy-1.0.5.dist-info/top_level.txt
kdriveclientpy-1.0.5.dist-info/RECORD
