Metadata-Version: 2.4
Name: kDriveClientPY
Version: 1.0.5
Summary: Python SDK for Infomaniak kDrive
Author-email: AnthonyChaussin <anthony.chaussin@ikmail.com>
License-Expression: MIT
Project-URL: Homepage, https://github.com/anthonychaussin/kDriveClientPY
Requires-Python: >=3.8
Requires-Dist: requests
